flaskeztest3/__init__.py
flaskeztest3/__main__.py
flaskeztest3/exceptions.py
flaskeztest3/eztest.py
flaskeztest3/eztestcase.py
flaskeztest3/eztestsuite.py
flaskeztest3/helpers.py
flaskeztest3-0.3.5.dist-info/LICENSE.md
flaskeztest3-0.3.5.dist-info/METADATA
flaskeztest3-0.3.5.dist-info/WHEEL
flaskeztest3-0.3.5.dist-info/entry_points.txt
flaskeztest3-0.3.5.dist-info/top_level.txt
flaskeztest3-0.3.5.dist-info/RECORD
